dictionary/__init__.py
dictionary/jieba_expanded_dict.txt
dictionary/special_chars.csv
dictionary/weibo_stopwords1_regex.csv
dictionary/weibo_stopwords2_regex.csv
weibo_preprocess_toolkit/__init__.py
weibo_preprocess_toolkit/toolkit.py
weibo_preprocess_toolkit/__pycache__/__init__.cpython-37.pyc
weibo_preprocess_toolkit/__pycache__/toolkit.cpython-37.pyc
weibo_preprocess_toolkit/dictionary/__init__.py
weibo_preprocess_toolkit/dictionary/jieba_expanded_dict.txt
weibo_preprocess_toolkit/dictionary/special_chars.csv
weibo_preprocess_toolkit/dictionary/stop_words.txt
weibo_preprocess_toolkit/dictionary/weibo_stopwords1_regex.csv
weibo_preprocess_toolkit/dictionary/weibo_stopwords2_regex.csv
weibo_preprocess_toolkit/lib/__init__.py
weibo_preprocess_toolkit/lib/langconv.py
weibo_preprocess_toolkit/lib/zh_wiki.py
weibo_preprocess_toolkit/lib/__pycache__/__init__.cpython-37.pyc
weibo_preprocess_toolkit/lib/__pycache__/langconv.cpython-37.pyc
weibo_preprocess_toolkit/lib/__pycache__/zh_wiki.cpython-37.pyc
weibo_preprocess_toolkit-1.1.0.dist-info/LICENSE
weibo_preprocess_toolkit-1.1.0.dist-info/METADATA
weibo_preprocess_toolkit-1.1.0.dist-info/WHEEL
weibo_preprocess_toolkit-1.1.0.dist-info/top_level.txt
weibo_preprocess_toolkit-1.1.0.dist-info/RECORD
