Metadata-Version: 2.1
Name: weibo-preprocess-toolkit
Version: 1.1.0
Summary: Weibo Preprocess Toolkit.
Home-page: https://github.com/wansho/weibo-preprocess-toolkit
Author: wansho
Author-email: wanshojs@gmail.com
License: MIT
Platform: UNKNOWN
Classifier: Development Status :: 4 - Beta
Classifier: Programming Language :: Python :: 3
Classifier: License :: OSI Approved :: MIT License
Classifier: Operating System :: OS Independent
Requires-Python: >=3
Requires-Dist: jieba (>=0.39)
